tests/__init__.py
tests/test_tools.py
wftools/__init__.py
wftools/api/__init__.py
wftools/api/tools.py
wftools/core/ToolsType.py
wftools/core/__init__.py
wftools/lib/__init__.py
wftools/lib/tools/__init__.py
wftools/lib/tools/lottery8ticket.py
wftools/lib/tools/pwd4wifi_service.py
wftools/lib/tools/qoute_dict_create_article.py
wftools/lib/tools/weather_city_code.py
wftools/lib/tools/weather_service.py
wftools-0.0.10.dist-info/LICENSE
wftools-0.0.10.dist-info/METADATA
wftools-0.0.10.dist-info/WHEEL
wftools-0.0.10.dist-info/top_level.txt
wftools-0.0.10.dist-info/RECORD
