Metadata-Version: 2.1
Name: wftools
Version: 0.0.10
Summary: pip install wftools
Home-page: https://www.python-office.com/
Author: CoderWanFeng
Author-email: 1957875073@qq.com
License: MIT
Project-URL: Bug Tracker, https://github.com/CoderWanFeng/wftools/issues
Project-URL: Documentation, https://github.com/CoderWanFeng/wftools/blob/master/README.md
Project-URL: Source Code, https://github.com/CoderWanFeng/wftools
Platform: any
Requires-Python: >=3.7
License-File: LICENSE
Requires-Dist: translate
Requires-Dist: qrcode
Requires-Dist: pywifi
Requires-Dist: speedtest-cli
Requires-Dist: pofile
Requires-Dist: loguru
